[
    {
        "id": 1,
        "title": "Suite Room",
        "description": "Far far away, behind the word mountains, far from the countries Vokalia and Consonantia, there live the blind texts.",
        "priceCurrency": "R$ 200,00/night",
        "image": "https://picsum.photos/1920",
        "people": 2,
        "beds": 1,
        "type": "suite",
        "price": "200"
    },
    {
        "id": 2,
        "title": "Deluxe Room",
        "description": "A small river named Duden flows by their place and supplies it with the necessary regelialia.",
        "priceCurrency": "R$ 150,00/night",
        "image": "https://picsum.photos/1920",
        "people": 2,
        "beds": 1,
        "type": "deluxe",
        "price": "150"
    },
    {
        "id": 3,
        "title": "Standard Room",
        "description": "It is a paradisematic country, in which roasted parts of sentences fly into your mouth. Even the all-powerful Pointing has no control about the blind texts it is an almost unorthographic life.",
        "price": "100",
        "image": "https://picsum.photos/1920",
        "people": 3,
        "beds": 1,
        "type": "standard",
        "priceCurrency": "R$ 100,00/night"
    },
    {
        "id": 4,
        "title": "Economy Room",
        "description": "On her way she met a copy. The copy warned the Little Blind Text, that where it came from it would have been rewritten a thousand times and everything that was left from its origin would be the word 'and' and the Little Blind Text should turn around and return to its own, safe country.",
        "price": "80",
        "image": "https://picsum.photos/1920",
        "people": 2,
        "beds": 1,
        "type": "economy",
        "priceCurrency": "R$ 80,00/night"
    },
    {
        "id": 5,
        "title": "Presidential Room",
        "description": "But nothing the copy said could convince her and so it didn’t take long until a few insidious Copy Writers ambushed her, made her discover with their mad creator, how to make her own book. It’s a long story, short she found herself in her own world.",
        "price": "300",
        "image": "https://picsum.photos/1920",
        "people": 2,
        "beds": 1,
        "type": "presidential",
        "priceCurrency": "R$ 300,00/night"
    },
    {
        "id": 6,
        "title": "Presidential Room",
        "description": "But nothing the copy said could convince her and so it didn’t take long until a few insidious Copy Writers ambushed her, made her discover with their mad creator, how to make her own book. It’s a long story, short she found herself in her own world.",
        "price": "300",
        "image": "https://picsum.photos/1920",
        "people": 2,
        "beds": 1,
        "type": "presidential",
        "priceCurrency": "R$ 300,00/night"
    }

]
